[
    {
        "productId": "1001",
        "head_points": [
            { "head_name": "Brand", "head_value": "Dell" },
            { "head_name": "Model", "head_value": "XPS 13" },
            { "head_name": "RAM", "head_value": "16GB" },
            { "head_name": "Storage", "head_value": "512GB SSD" },
            { "head_name": "Processor", "head_value": "Intel Core i7" }
        ]
    },
    {
        "productId": "1002",
        "head_points": [
            { "head_name": "Brand", "head_value": "Samsung" },
            { "head_name": "Model", "head_value": "Galaxy S21" },
            { "head_name": "RAM", "head_value": "8GB" },
            { "head_name": "Storage", "head_value": "128GB" },
            { "head_name": "Camera", "head_value": "64MP" },
            { "head_name": "Battery", "head_value": "4000mAh" }
        ]
    },
    {
        "productId": "1003",
        "head_points": [
            { "head_name": "Brand", "head_value": "Apple" },
            { "head_name": "Model", "head_value": "iPad Pro" },
            { "head_name": "Screen Size", "head_value": "12.9 inches" },
            { "head_name": "Storage", "head_value": "256GB" },
            { "head_name": "Processor", "head_value": "Apple M1" }
        ]
    },
    {
        "productId": "1004",
        "head_points": [
            { "head_name": "Brand", "head_value": "Apple" },
            { "head_name": "Model", "head_value": "Watch Series 6" },
            { "head_name": "Case Size", "head_value": "44mm" },
            { "head_name": "Connectivity", "head_value": "GPS + Cellular" }
        ]
    },
    {
        "productId": "1005",
        "head_points": [
            { "head_name": "Brand", "head_value": "Sony" },
            { "head_name": "Model", "head_value": "WH-1000XM4" },
            { "head_name": "Type", "head_value": "Over-Ear" },
            { "head_name": "Noise Cancelling", "head_value": "Yes" }
        ]
    },
    {
        "productId": "1006",
        "head_points": [
            { "head_name": "Brand", "head_value": "Canon" },
            { "head_name": "Model", "head_value": "EOS R5" },
            { "head_name": "Sensor", "head_value": "45MP Full-Frame" },
            { "head_name": "Video Resolution", "head_value": "8K" },
            { "head_name": "Lens Mount", "head_value": "RF" }
        ]
    },
    {
        "productId": "1007",
        "head_points": [
            { "head_name": "Brand", "head_value": "HP" },
            { "head_name": "Model", "head_value": "LaserJet Pro" },
            { "head_name": "Type", "head_value": "Laser Printer" },
            { "head_name": "Connectivity", "head_value": "WiFi" }
        ]
    },
    {
        "productId": "1008",
        "head_points": [
            { "head_name": "Brand", "head_value": "LG" },
            { "head_name": "Model", "head_value": "UltraWide" },
            { "head_name": "Size", "head_value": "34 inches" },
            { "head_name": "Resolution", "head_value": "3440 x 1440" },
            { "head_name": "Refresh Rate", "head_value": "144Hz" }
        ]
    },
    {
        "productId": "1009",
        "head_points": [
            { "head_name": "Brand", "head_value": "Logitech" },
            { "head_name": "Model", "head_value": "MX Keys" },
            { "head_name": "Type", "head_value": "Wireless" },
            { "head_name": "Backlit", "head_value": "Yes" }
        ]
    },
    {
        "productId": "1010",
        "head_points": [
            { "head_name": "Brand", "head_value": "Logitech" },
            { "head_name": "Model", "head_value": "MX Master 3" },
            { "head_name": "Type", "head_value": "Wireless" },
            { "head_name": "DPI", "head_value": "4000" }
        ]
    },
    {
        "productId": "1011",
        "head_points": [
            { "head_name": "Brand", "head_value": "Netgear" },
            { "head_name": "Model", "head_value": "Nighthawk" },
            { "head_name": "Type", "head_value": "WiFi 6 Router" },
            { "head_name": "Speed", "head_value": "AX6000" }
        ]
    },
    {
        "productId": "1012",
        "head_points": [
            { "head_name": "Brand", "head_value": "JBL" },
            { "head_name": "Model", "head_value": "Flip 5" },
            { "head_name": "Type", "head_value": "Portable Speaker" },
            { "head_name": "Waterproof", "head_value": "IPX7" }
        ]
    },
    {
        "productId": "1013",
        "head_points": [
            { "head_name": "Brand", "head_value": "Seagate" },
            { "head_name": "Model", "head_value": "Backup Plus" },
            { "head_name": "Capacity", "head_value": "2TB" },
            { "head_name": "Type", "head_value": "External HDD" }
        ]
    },
    {
        "productId": "1014",
        "head_points": [
            { "head_name": "Brand", "head_value": "SanDisk" },
            { "head_name": "Model", "head_value": "Ultra" },
            { "head_name": "Capacity", "head_value": "128GB" },
            { "head_name": "Type", "head_value": "USB 3.0" }
        ]
    },
    {
        "productId": "1015",
        "head_points": [
            { "head_name": "Brand", "head_value": "SanDisk" },
            { "head_name": "Model", "head_value": "Extreme" },
            { "head_name": "Capacity", "head_value": "256GB" },
            { "head_name": "Type", "head_value": "MicroSD" }
        ]
    },
    {
        "productId": "1016",
        "head_points": [
            { "head_name": "Brand", "head_value": "Sony" },
            { "head_name": "Model", "head_value": "PlayStation 5" },
            { "head_name": "Storage", "head_value": "825GB SSD" },
            { "head_name": "Resolution", "head_value": "4K" }
        ]
    },
    {
        "productId": "1017",
        "head_points": [
            { "head_name": "Brand", "head_value": "Oculus" },
            { "head_name": "Model", "head_value": "Quest 2" },
            { "head_name": "Storage", "head_value": "256GB" },
            { "head_name": "Resolution", "head_value": "1832 x 1920 per eye" }
        ]
    },
    {
        "productId": "1018",
        "head_points": [
            { "head_name": "Brand", "head_value": "Amazon" },
            { "head_name": "Model", "head_value": "Echo Show 8" },
            { "head_name": "Screen Size", "head_value": "8 inches" },
            { "head_name": "Assistant", "head_value": "Alexa" }
        ]
    },
    {
        "productId": "1019",
        "head_points": [
            { "head_name": "Brand", "head_value": "DJI" },
            { "head_name": "Model", "head_value": "Mavic Air 2" },
            { "head_name": "Camera", "head_value": "48MP" },
            { "head_name": "Video Resolution", "head_value": "4K" }
        ]
    },
    {
        "productId": "1020",
        "head_points": [
            { "head_name": "Brand", "head_value": "Fitbit" },
            { "head_name": "Model", "head_value": "Charge 4" },
            { "head_name": "Heart Rate Monitor", "head_value": "Yes" },
            { "head_name": "GPS", "head_value": "Yes" }
        ]
    },
    {
        "productId": "1021",
        "head_points": [
            { "head_name": "Brand", "head_value": "Microsoft" },
            { "head_name": "Model", "head_value": "Surface Pro 7" },
            { "head_name": "Storage", "head_value": "128GB SSD" },
            { "head_name": "RAM", "head_value": "8GB" }
        ]
    },
    {
        "productId": "1022",
        "head_points": [
            { "head_name": "Brand", "head_value": "Nikon" },
            { "head_name": "Model", "head_value": "Z6 II" },
            { "head_name": "Sensor", "head_value": "24.5MP Full-Frame" },
            { "head_name": "Video Resolution", "head_value": "4K" },
            { "head_name": "Lens Mount", "head_value": "Z Mount" }
        ]
    },
    {
        "productId": "1023",
        "head_points": [
            { "head_name": "Brand", "head_value": "Philips" },
            { "head_name": "Model", "head_value": "Hue" },
            { "head_name": "Type", "head_value": "Smart Light Bulb" },
            { "head_name": "Connectivity", "head_value": "Bluetooth" }
        ]
    },
    {
        "productId": "1024",
        "head_points": [
            { "head_name": "Brand", "head_value": "Nest" },
            { "head_name": "Model", "head_value": "Learning Thermostat" },
            { "head_name": "Type", "head_value": "Smart Thermostat" },
            { "head_name": "Connectivity", "head_value": "WiFi" }
        ]
    },
    {
        "productId": "1025",
        "head_points": [
            { "head_name": "Brand", "head_value": "Arlo" },
            { "head_name": "Model", "head_value": "Pro 4" },
            { "head_name": "Resolution", "head_value": "2K" },
            { "head_name": "Field of View", "head_value": "160 degrees" }
        ]
    },
    {
        "productId": "1026",
        "head_points": [
            { "head_name": "Brand", "head_value": "Breville" },
            { "head_name": "Model", "head_value": "Smart Kettle" },
            { "head_name": "Capacity", "head_value": "1.7L" },
            { "head_name": "Power", "head_value": "1500W" }
        ]
    },
    {
        "productId": "1027",
        "head_points": [
            { "head_name": "Brand", "head_value": "Panasonic" },
            { "head_name": "Model", "head_value": "NN-SN966S" },
            { "head_name": "Capacity", "head_value": "2.2 cu ft" },
            { "head_name": "Power", "head_value": "1250W" }
        ]
    },
    {
        "productId": "1028",
        "head_points": [
            { "head_name": "Brand", "head_value": "Samsung" },
            { "head_name": "Model", "head_value": "Family Hub" },
            { "head_name": "Capacity", "head_value": "26.7 cu ft" },
            { "head_name": "Type", "head_value": "French Door" }
        ]
    },
    {
        "productId": "1029",
        "head_points": [
            { "head_name": "Brand", "head_value": "LG" },
            { "head_name": "Model", "head_value": "TWINWash" },
            { "head_name": "Capacity", "head_value": "4.5 cu ft" },
            { "head_name": "Type", "head_value": "Front Load" }
        ]
    },
    {
        "productId": "1030",
        "head_points": [
            { "head_name": "Brand", "head_value": "Carrier" },
            { "head_name": "Model", "head_value": "Infinity" },
            { "head_name": "Capacity", "head_value": "2.5 Ton" },
            { "head_name": "Type", "head_value": "Central Air Conditioner" }
        ]
    }
]
